ccsdoc/__init__.py
ccsdoc/command.py
ccsdoc/parameter.py
ccsdoc/parser.py
ccsdoc/text.py
ccsdoc/scripts/__init__.py
ccsdoc/scripts/cli.py
ccsdoc/scripts/convert.py
ccsdoc/scripts/parse.py
ccsdoc/scripts/trending.py
ccsdoc-0.2.0.dist-info/LICENSE
ccsdoc-0.2.0.dist-info/METADATA
ccsdoc-0.2.0.dist-info/WHEEL
ccsdoc-0.2.0.dist-info/entry_points.txt
ccsdoc-0.2.0.dist-info/top_level.txt
ccsdoc-0.2.0.dist-info/RECORD
