Metadata-Version: 2.1
Name: ccsdoc
Version: 0.2.0
Summary: Parser tools for generating CCS Java documentation
Home-page: https://github.com/aboucaud/command-doc-generator
Author: Alexandre Boucaud
Author-email: aboucaud@apc.in2p3.fr
License: BSD 3-Clause License
Project-URL: Bug Tracker, https://github.com/aboucaud/command-doc-generator/issues
Requires-Python: >=3.6
License-File: LICENSE
Requires-Dist: click
Requires-Dist: pandas >=1.0
Provides-Extra: test
Requires-Dist: mypy ; extra == 'test'
Requires-Dist: pytest ; extra == 'test'
Requires-Dist: pytest-cov ; extra == 'test'
